s3_local_endpoint/__init__.py
s3_local_endpoint/s3_local_endpoint.py
s3_local_endpoint/tests/__init__.py
s3_local_endpoint/tests/tests_s3_local_endpoint.py
s3_local_endpoint-1.0.4.dist-info/LICENSE
s3_local_endpoint-1.0.4.dist-info/METADATA
s3_local_endpoint-1.0.4.dist-info/WHEEL
s3_local_endpoint-1.0.4.dist-info/top_level.txt
s3_local_endpoint-1.0.4.dist-info/RECORD
